{"lcarrara":[{"floor":-1,"zone":-1,"offset":0},{"floor":1,"zone":1,"offset":478800},{"floor":1,"zone":4,"offset":478850},{"floor":2,"zone":4,"offset":478892},{"floor":3,"zone":4,"offset":478923},{"floor":3,"zone":1,"offset":478925},{"floor":3,"zone":6,"offset":478940},{"floor":3,"zone":3,"offset":478948},{"floor":3,"zone":6,"offset":486310},{"floor":3,"zone":1,"offset":486317},{"floor":3,"zone":4,"offset":486336},{"floor":2,"zone":4,"offset":486378},{"floor":1,"zone":4,"offset":486409},{"floor":-1,"zone":-1,"offset":486411},{"floor":-1,"zone":-1,"offset":86400}]}